CHANGES.txt
MANIFEST.in
README.txt
setup.py
src/plone/__init__.py
src/plone.recipe.zope2zeoserver.egg-info/PKG-INFO
src/plone.recipe.zope2zeoserver.egg-info/SOURCES.txt
src/plone.recipe.zope2zeoserver.egg-info/dependency_links.txt
src/plone.recipe.zope2zeoserver.egg-info/entry_points.txt
src/plone.recipe.zope2zeoserver.egg-info/namespace_packages.txt
src/plone.recipe.zope2zeoserver.egg-info/not-zip-safe
src/plone.recipe.zope2zeoserver.egg-info/requires.txt
src/plone.recipe.zope2zeoserver.egg-info/top_level.txt
src/plone/recipe/__init__.py
src/plone/recipe/zope2zeoserver/__init__.py
src/plone/recipe/zope2zeoserver/ctl.py
src/plone/recipe/zope2zeoserver/pack.py
src/plone/recipe/zope2zeoserver/runzeo.bat
src/plone/recipe/zope2zeoserver/zeoservice.py.in
src/plone/recipe/zope2zeoserver/tests/__init__.py
src/plone/recipe/zope2zeoserver/tests/test_docs.py
src/plone/recipe/zope2zeoserver/tests/zeoserver-win32.txt
src/plone/recipe/zope2zeoserver/tests/zeoserver.txt
src/plone/recipe/zope2zeoserver/tests/zope2/lib/python/ZEO/__init__.py
src/plone/recipe/zope2zeoserver/tests/zope2/lib/python/ZEO/mkzeoinst.py
src/plone/recipe/zope2zeoserver/tests/zope2/utilities/ZODBTools/repozo.py