Metadata-Version: 1.1
Name: plone.recipe.zope2zeoserver
Version: 1.5
Summary: ZC Buildout recipe for installing a Zope 2 ZEO server
Home-page: http://svn.plone.org/svn/collective/buildout/plone.recipe.zope2zeoserver
Author: Hanno Schlichting
Author-email: hannosch@plone.org
License: ZPL 2.1
Keywords: zope2 buildout
Platform: UNKNOWN
Classifier: License :: OSI Approved :: Zope Public License
Classifier: Framework :: Buildout
Classifier: Framework :: Zope2
Classifier: Programming Language :: Python
